together_cli/__init__.py
together_cli/src/__init__.py
together_cli/src/constants.py
together_cli/src/model.py
together_cli/src/script_composer.py
together_cli/src/system.py
together_cli/src/utility.py
together_cli/src/backend/__init__.py
together_cli/src/backend/docker.py
together_cli/src/backend/singularity.py
together_cli/src/clusters/__init__.py
together_cli/src/clusters/baremetal.py
together_cli/src/clusters/slurm.py
together_cli/src/core/__init__.py
together_cli/src/core/config.py
together_cli/src/core/instances.py
together_cli/src/core/models.py
together_cli/src/core/render.py
together_cli-0.0.84.data/scripts/together-cli
together_cli-0.0.84.dist-info/METADATA
together_cli-0.0.84.dist-info/WHEEL
together_cli-0.0.84.dist-info/top_level.txt
together_cli-0.0.84.dist-info/RECORD
