Metadata-Version: 2.1
Name: together-cli
Version: 0.0.84
Summary: Together cli is a tool to help you join together computer
Author: togethercomputer
Author-email: support@together.xyz
Requires-Dist: typer
Requires-Dist: requests
Requires-Dist: rich
Requires-Dist: loguru
Requires-Dist: huggingface-hub
Requires-Dist: pynvml
